strategizer/__init__.py
strategizer/strategies.py
strategizer-0.0.2.dist-info/LICENSE
strategizer-0.0.2.dist-info/METADATA
strategizer-0.0.2.dist-info/WHEEL
strategizer-0.0.2.dist-info/top_level.txt
strategizer-0.0.2.dist-info/RECORD
