Metadata-Version: 2.1
Name: strategizer
Version: 0.0.2
Summary: Strategizer is a Python framework for executing and evaluating financial trading strategies with customizable signal generation.
Home-page: https://github.com/nathanschmidt89/strategizer
Author: Nathan Schmidt
Author-email: Nathan Schmidt <nathan.schmidt.ns89@gmail.com>
Project-URL: Homepage, https://github.com/nathanschmidt89/strategizer
Project-URL: Issues, https://github.com/nathanschmidt89/strategizer/issues
Classifier: Programming Language :: Python :: 3
Classifier: License :: OSI Approved :: The Unlicense (Unlicense)
Classifier: Operating System :: OS Independent
Requires-Python: >=3.12
License-File: LICENSE
